cnspy_timestamp_association/TimestampAssociation.py
cnspy_timestamp_association/__init__.py
test/__init__.py
test/test_TimestampAssociation.py
cnspy_timestamp_association-0.2.1.dist-info/LICENCE
cnspy_timestamp_association-0.2.1.dist-info/METADATA
cnspy_timestamp_association-0.2.1.dist-info/WHEEL
cnspy_timestamp_association-0.2.1.dist-info/top_level.txt
cnspy_timestamp_association-0.2.1.dist-info/RECORD
