Metadata-Version: 2.1
Name: cnspy_timestamp_association
Version: 0.2.1
Summary: Associates vectors of timestamps.
Home-page: https://github.com/aau-cns/cnspy_timestamp_association/
Author: Roland Jung
Author-email: roland.jung@aau.at
Project-URL: Bug Tracker, https://github.com/aau-cns/cnspy_timestamp_association/issues
Classifier: Development Status :: 4 - Beta
Classifier: Intended Audience :: Developers
Classifier: Programming Language :: Python :: 3
Classifier: License :: OSI Approved :: GNU General Public License v3 (GPLv3)
Classifier: Operating System :: OS Independent
Requires-Python: >=3.6
License-File: LICENCE
Requires-Dist: numpy
